ysgnmi/__init__.py
ysgnmi/_version.py
ysgnmi/apps.py
ysgnmi/device_plugin.py
ysgnmi/gnmi.py
ysgnmi/gnmi_util.py
ysgnmi/urls.py
ysgnmi/views.py
ysgnmi/yangtree.py
ysgnmi/static/ysgnmi/css/ysgnmi.css
ysgnmi/static/ysgnmi/docs/.buildinfo
ysgnmi/static/ysgnmi/docs/environment.pickle
ysgnmi/static/ysgnmi/docs/genindex.fjson
ysgnmi/static/ysgnmi/docs/genindex.html
ysgnmi/static/ysgnmi/docs/globalcontext.json
ysgnmi/static/ysgnmi/docs/index.fjson
ysgnmi/static/ysgnmi/docs/index.html
ysgnmi/static/ysgnmi/docs/last_build
ysgnmi/static/ysgnmi/docs/objects.inv
ysgnmi/static/ysgnmi/docs/search.fjson
ysgnmi/static/ysgnmi/docs/search.html
ysgnmi/static/ysgnmi/docs/searchindex.js
ysgnmi/static/ysgnmi/docs/searchindex.json
ysgnmi/static/ysgnmi/docs/.doctrees/environment.pickle
ysgnmi/static/ysgnmi/docs/.doctrees/index.doctree
ysgnmi/static/ysgnmi/docs/_images/capabilities.png
ysgnmi/static/ysgnmi/docs/_images/devprofile_enablement.png
ysgnmi/static/ysgnmi/docs/_images/get_json.png
ysgnmi/static/ysgnmi/docs/_images/module_selection.png
ysgnmi/static/ysgnmi/docs/_images/modules_loaded.png
ysgnmi/static/ysgnmi/docs/_images/rpc_options.png
ysgnmi/static/ysgnmi/docs/_images/rpc_run_get.png
ysgnmi/static/ysgnmi/docs/_images/tree_get.png
ysgnmi/static/ysgnmi/docs/_images/tree_set.png
ysgnmi/static/ysgnmi/docs/_images/yangset_and_devprofile.png
ysgnmi/static/ysgnmi/docs/_sources/index.rst.txt
ysgnmi/static/ysgnmi/docs/_static/basic.css
ysgnmi/static/ysgnmi/docs/_static/doctools.js
ysgnmi/static/ysgnmi/docs/_static/documentation_options.js
ysgnmi/static/ysgnmi/docs/_static/file.png
ysgnmi/static/ysgnmi/docs/_static/language_data.js
ysgnmi/static/ysgnmi/docs/_static/minus.png
ysgnmi/static/ysgnmi/docs/_static/plus.png
ysgnmi/static/ysgnmi/docs/_static/pygments.css
ysgnmi/static/ysgnmi/docs/_static/searchtools.js
ysgnmi/static/ysgnmi/docs/_static/sphinx_highlight.js
ysgnmi/static/ysgnmi/docs/_static/css/badge_only.css
ysgnmi/static/ysgnmi/docs/_static/css/theme.css
yangsuite_gnmi-2.7.15.dist-info/LICENSE.txt
yangsuite_gnmi-2.7.15.dist-info/METADATA
yangsuite_gnmi-2.7.15.dist-info/WHEEL
yangsuite_gnmi-2.7.15.dist-info/entry_points.txt
yangsuite_gnmi-2.7.15.dist-info/top_level.txt
yangsuite_gnmi-2.7.15.dist-info/RECORD
