Metadata-Version: 2.1
Name: yangsuite-gnmi
Version: 2.7.15
Summary: gRPC / gNMI protocol support for YANG Suite
Home-page: https://developer.cisco.com/yangsuite
Author: Glenn Matthews
Author-email: yangsuite-support-ext@cisco.com
License: Cisco End User License Agreement
Requires-Python: >=3.6
License-File: LICENSE.txt
Requires-Dist: yangsuite >=3.0.0
Requires-Dist: yangsuite-filemanager <2.0.0
Requires-Dist: yangsuite-devices <3.0.0,>=2.7.0
Requires-Dist: yangsuite-yangtree >=2.0.0
Requires-Dist: yangsuite-netconf >=1.17.6
Requires-Dist: yang.connector
